mkdocs_static_i18n/__init__.py
mkdocs_static_i18n/config.py
mkdocs_static_i18n/folder.py
mkdocs_static_i18n/plugin.py
mkdocs_static_i18n/reconfigure.py
mkdocs_static_i18n/suffix.py
mkdocs_static_i18n/utils.py
mkdocs_static_i18n/custom_i18n_sitemap/sitemap.xml
mkdocs_static_i18n-1.2.1.dist-info/METADATA
mkdocs_static_i18n-1.2.1.dist-info/WHEEL
mkdocs_static_i18n-1.2.1.dist-info/entry_points.txt
mkdocs_static_i18n-1.2.1.dist-info/licenses/LICENSE
mkdocs_static_i18n-1.2.1.dist-info/RECORD
