Metadata-Version: 2.1
Name: mkdocs-static-i18n
Version: 1.2.1
Summary: MkDocs i18n plugin using static translation markdown files
Project-URL: Documentation, https://github.com/ultrabug/mkdocs-static-i18n#readme
Project-URL: Download, https://github.com/ultrabug/mkdocs-static-i18n/tags
Project-URL: Funding, https://ultrabug.fr/#support-me
Project-URL: Homepage, https://github.com/ultrabug/mkdocs-static-i18n
Project-URL: Source, https://github.com/ultrabug/mkdocs-static-i18n
Project-URL: Tracker, https://github.com/ultrabug/mkdocs-static-i18n/issues
Author-email: Ultrabug <ultrabug@ultrabug.net>
License-Expression: MIT
License-File: LICENSE
Classifier: License :: OSI Approved :: MIT License
Classifier: Operating System :: POSIX :: Linux
Classifier: Programming Language :: Python
Classifier: Programming Language :: Python :: 3
Classifier: Programming Language :: Python :: 3 :: Only
Classifier: Programming Language :: Python :: 3.7
Classifier: Programming Language :: Python :: 3.8
Classifier: Programming Language :: Python :: 3.9
Classifier: Programming Language :: Python :: 3.10
Classifier: Programming Language :: Python :: 3.11
Classifier: Topic :: Software Development :: Libraries :: Python Modules
Requires-Python: >=3.7
Requires-Dist: mkdocs>=1.5.2
Provides-Extra: material
Requires-Dist: mkdocs-material>=9.2.5; extra == 'material'
